<?xml version="1.0" encoding="UTF-8" ?>
<!DOCTYPE mapper PUBLIC "-//mybatis.org//DTD Mapper 3.0//EN"
        "http://mybatis.org/dtd/mybatis-3-mapper.dtd">

<mapper namespace="com.sias.schedule.mapper.StudentMapper">

    <!-- 结果映射 -->
    <resultMap id="StudentResultMap" type="Student">
        <id property="id" column="id"/>
        <result property="studentId" column="student_id"/>
        <result property="internalId" column="internal_id"/>
        <result property="name" column="name"/>
        <result property="lastSyncAt" column="last_sync_at"/>
        <result property="createdAt" column="created_at"/>
    </resultMap>

    <!-- 根据学号查询学生 -->
    <select id="findByStudentId" resultMap="StudentResultMap">
        SELECT * FROM t_student WHERE student_id = #{studentId}
    </select>

    <!-- 判断学号是否存在 -->
    <select id="existsByStudentId" resultType="boolean">
        SELECT COUNT(1) > 0 FROM t_student WHERE student_id = #{studentId}
    </select>

    <!-- 插入学生 -->
    <insert id="insert" parameterType="Student" useGeneratedKeys="true" keyProperty="id">
        INSERT INTO t_student (student_id, internal_id, name, last_sync_at, created_at)
        VALUES (#{studentId}, #{internalId}, #{name}, #{lastSyncAt}, NOW())
    </insert>

    <!-- 更新学生 -->
    <update id="update" parameterType="Student">
        UPDATE t_student
        SET internal_id = #{internalId},
            name = #{name},
            last_sync_at = #{lastSyncAt}
        WHERE student_id = #{studentId}
    </update>

    <!-- 插入或更新学生 -->
    <insert id="insertOrUpdate" parameterType="Student">
        INSERT INTO t_student (student_id, internal_id, name, last_sync_at, created_at)
        VALUES (#{studentId}, #{internalId}, #{name}, #{lastSyncAt}, NOW())
        ON DUPLICATE KEY UPDATE
            internal_id = VALUES(internal_id),
            name = VALUES(name),
            last_sync_at = VALUES(last_sync_at)
    </insert>

</mapper>
